proxmox_backup_rdx/__init__.py
proxmox_backup_rdx/main.py
proxmox_backup_rdx/models/__init__.py
proxmox_backup_rdx/models/datastore.py
proxmox_backup_rdx/models/prunejob.py
proxmox_backup_rdx/models/syncjob.py
proxmox_backup_rdx/models/utils.py
proxmox_backup_rdx-2.0.13.dist-info/LICENCE
proxmox_backup_rdx-2.0.13.dist-info/METADATA
proxmox_backup_rdx-2.0.13.dist-info/WHEEL
proxmox_backup_rdx-2.0.13.dist-info/entry_points.txt
proxmox_backup_rdx-2.0.13.dist-info/top_level.txt
proxmox_backup_rdx-2.0.13.dist-info/RECORD
