Metadata-Version: 2.1
Name: proxmox-backup-rdx
Version: 2.0.13
Summary: Sync proxmox backup datastore to RDX
Author-email: Mathieu Fruchet <mathieu.fruchet@greenitsolutions.fr>
Maintainer-email: Green IT Solutions <support@greenitsolutions.fr>
Requires-Python: >=3.9
License-File: LICENCE
